{
  "provinces": [
    { "id": "metro-manila", "name": "Metro Manila", "region": "NCR" },
    { "id": "abra", "name": "Abra", "region": "CAR" },
    { "id": "apayao", "name": "Apayao", "region": "CAR" },
    { "id": "benguet", "name": "Benguet", "region": "CAR" },
    { "id": "ifugao", "name": "Ifugao", "region": "CAR" },
    { "id": "kalinga", "name": "Kalinga", "region": "CAR" },
    { "id": "mountain-province", "name": "Mountain Province", "region": "CAR" },
    { "id": "ilocos-norte", "name": "Ilocos Norte", "region": "Region I" },
    { "id": "ilocos-sur", "name": "Ilocos Sur", "region": "Region I" },
    { "id": "la-union", "name": "La Union", "region": "Region I" },
    { "id": "pangasinan", "name": "Pangasinan", "region": "Region I" },
    { "id": "batanes", "name": "Batanes", "region": "Region II" },
    { "id": "cagayan", "name": "Cagayan", "region": "Region II" },
    { "id": "isabela", "name": "Isabela", "region": "Region II" },
    { "id": "nueva-vizcaya", "name": "Nueva Vizcaya", "region": "Region II" },
    { "id": "quirino", "name": "Quirino", "region": "Region II" },
    { "id": "aurora", "name": "Aurora", "region": "Region III" },
    { "id": "bataan", "name": "Bataan", "region": "Region III" },
    { "id": "bulacan", "name": "Bulacan", "region": "Region III" },
    { "id": "nueva-ecija", "name": "Nueva Ecija", "region": "Region III" },
    { "id": "pampanga", "name": "Pampanga", "region": "Region III" },
    { "id": "tarlac", "name": "Tarlac", "region": "Region III" },
    { "id": "zambales", "name": "Zambales", "region": "Region III" },
    { "id": "batangas", "name": "Batangas", "region": "Region IV-A" },
    { "id": "cavite", "name": "Cavite", "region": "Region IV-A" },
    { "id": "laguna", "name": "Laguna", "region": "Region IV-A" },
    { "id": "quezon", "name": "Quezon", "region": "Region IV-A" },
    { "id": "rizal", "name": "Rizal", "region": "Region IV-A" },
    { "id": "marinduque", "name": "Marinduque", "region": "Region IV-B" },
    { "id": "occidental-mindoro", "name": "Occidental Mindoro", "region": "Region IV-B" },
    { "id": "oriental-mindoro", "name": "Oriental Mindoro", "region": "Region IV-B" },
    { "id": "palawan", "name": "Palawan", "region": "Region IV-B" },
    { "id": "romblon", "name": "Romblon", "region": "Region IV-B" },
    { "id": "albay", "name": "Albay", "region": "Region V" },
    { "id": "camarines-norte", "name": "Camarines Norte", "region": "Region V" },
    { "id": "camarines-sur", "name": "Camarines Sur", "region": "Region V" },
    { "id": "catanduanes", "name": "Catanduanes", "region": "Region V" },
    { "id": "masbate", "name": "Masbate", "region": "Region V" },
    { "id": "sorsogon", "name": "Sorsogon", "region": "Region V" },
    { "id": "aklan", "name": "Aklan", "region": "Region VI" },
    { "id": "antique", "name": "Antique", "region": "Region VI" },
    { "id": "capiz", "name": "Capiz", "region": "Region VI" },
    { "id": "guimaras", "name": "Guimaras", "region": "Region VI" },
    { "id": "iloilo", "name": "Iloilo", "region": "Region VI" },
    { "id": "negros-occidental", "name": "Negros Occidental", "region": "Region VI" },
    { "id": "bohol", "name": "Bohol", "region": "Region VII" },
    { "id": "cebu", "name": "Cebu", "region": "Region VII" },
    { "id": "negros-oriental", "name": "Negros Oriental", "region": "Region VII" },
    { "id": "siquijor", "name": "Siquijor", "region": "Region VII" },
    { "id": "biliran", "name": "Biliran", "region": "Region VIII" },
    { "id": "eastern-samar", "name": "Eastern Samar", "region": "Region VIII" },
    { "id": "leyte", "name": "Leyte", "region": "Region VIII" },
    { "id": "northern-samar", "name": "Northern Samar", "region": "Region VIII" },
    { "id": "samar", "name": "Samar", "region": "Region VIII" },
    { "id": "southern-leyte", "name": "Southern Leyte", "region": "Region VIII" },
    { "id": "zamboanga-del-norte", "name": "Zamboanga del Norte", "region": "Region IX" },
    { "id": "zamboanga-del-sur", "name": "Zamboanga del Sur", "region": "Region IX" },
    { "id": "zamboanga-sibugay", "name": "Zamboanga Sibugay", "region": "Region IX" },
    { "id": "bukidnon", "name": "Bukidnon", "region": "Region X" },
    { "id": "camiguin", "name": "Camiguin", "region": "Region X" },
    { "id": "lanao-del-norte", "name": "Lanao del Norte", "region": "Region X" },
    { "id": "misamis-occidental", "name": "Misamis Occidental", "region": "Region X" },
    { "id": "misamis-oriental", "name": "Misamis Oriental", "region": "Region X" },
    { "id": "compostela-valley", "name": "Compostela Valley", "region": "Region XI" },
    { "id": "davao-del-norte", "name": "Davao del Norte", "region": "Region XI" },
    { "id": "davao-del-sur", "name": "Davao del Sur", "region": "Region XI" },
    { "id": "davao-oriental", "name": "Davao Oriental", "region": "Region XI" },
    { "id": "davao-occidental", "name": "Davao Occidental", "region": "Region XI" },
    { "id": "davao-de-oro", "name": "Davao de Oro", "region": "Region XI" },
    { "id": "north-cotabato", "name": "North Cotabato", "region": "Region XII" },
    { "id": "south-cotabato", "name": "South Cotabato", "region": "Region XII" },
    { "id": "sultan-kudarat", "name": "Sultan Kudarat", "region": "Region XII" },
    { "id": "sarangani", "name": "Sarangani", "region": "Region XII" },
    { "id": "agusan-del-norte", "name": "Agusan del Norte", "region": "Region XIII" },
    { "id": "agusan-del-sur", "name": "Agusan del Sur", "region": "Region XIII" },
    { "id": "surigao-del-norte", "name": "Surigao del Norte", "region": "Region XIII" },
    { "id": "surigao-del-sur", "name": "Surigao del Sur", "region": "Region XIII" },
    { "id": "dinagat-islands", "name": "Dinagat Islands", "region": "Region XIII" },
    { "id": "basilan", "name": "Basilan", "region": "BARMM" },
    { "id": "lanao-del-sur", "name": "Lanao del Sur", "region": "BARMM" },
    { "id": "maguindanao", "name": "Maguindanao", "region": "BARMM" },
    { "id": "sulu", "name": "Sulu", "region": "BARMM" },
    { "id": "tawi-tawi", "name": "Tawi-Tawi", "region": "BARMM" }
  ],
  "cities": {
    "metro-manila": [
      { "id": "caloocan", "name": "Caloocan" },
      { "id": "las-pinas", "name": "Las Piñas" },
      { "id": "makati", "name": "Makati" },
      { "id": "malabon", "name": "Malabon" },
      { "id": "mandaluyong", "name": "Mandaluyong" },
      { "id": "manila", "name": "Manila" },
      { "id": "marikina", "name": "Marikina" },
      { "id": "muntinlupa", "name": "Muntinlupa" },
      { "id": "navotas", "name": "Navotas" },
      { "id": "paranaque", "name": "Parañaque" },
      { "id": "pasay", "name": "Pasay" },
      { "id": "pasig", "name": "Pasig" },
      { "id": "pateros", "name": "Pateros" },
      { "id": "quezon-city", "name": "Quezon City" },
      { "id": "san-juan", "name": "San Juan" },
      { "id": "taguig", "name": "Taguig" },
      { "id": "valenzuela", "name": "Valenzuela" }
    ],
    "laguna": [
      { "id": "alaminos", "name": "Alaminos" },
      { "id": "bay", "name": "Bay" },
      { "id": "biñan", "name": "Biñan" },
      { "id": "cabuyao", "name": "Cabuyao" },
      { "id": "calamba", "name": "Calamba" },
      { "id": "calauan", "name": "Calauan" },
      { "id": "cavinti", "name": "Cavinti" },
      { "id": "famy", "name": "Famy" },
      { "id": "kalayaan", "name": "Kalayaan" },
      { "id": "liliw", "name": "Liliw" },
      { "id": "los-banos", "name": "Los Baños" },
      { "id": "luisiana", "name": "Luisiana" },
      { "id": "lumban", "name": "Lumban" },
      { "id": "mabitac", "name": "Mabitac" },
      { "id": "magdalena", "name": "Magdalena" },
      { "id": "majayjay", "name": "Majayjay" },
      { "id": "nagcarlan", "name": "Nagcarlan" },
      { "id": "paete", "name": "Paete" },
      { "id": "pagsanjan", "name": "Pagsanjan" },
      { "id": "pakil", "name": "Pakil" },
      { "id": "panukulan", "name": "Panukulan" },
      { "id": "pila", "name": "Pila" },
      { "id": "rizal", "name": "Rizal" },
      { "id": "san-pablo", "name": "San Pablo" },
      { "id": "san-pedro", "name": "San Pedro" },
      { "id": "santa-cruz", "name": "Santa Cruz" },
      { "id": "santa-maria", "name": "Santa Maria" },
      { "id": "santa-rosa", "name": "Santa Rosa" },
      { "id": "siniloan", "name": "Siniloan" },
      { "id": "victoria", "name": "Victoria" }
    ],
    "cavite": [
      { "id": "alfonso", "name": "Alfonso" },
      { "id": "amadeo", "name": "Amadeo" },
      { "id": "bacoor", "name": "Bacoor" },
      { "id": "carmona", "name": "Carmona" },
      { "id": "cavite-city", "name": "Cavite City" },
      { "id": "dasmarinas", "name": "Dasmariñas" },
      { "id": "general-emilio-aguinaldo", "name": "General Emilio Aguinaldo" },
      { "id": "general-mariano-alvarez", "name": "General Mariano Alvarez" },
      { "id": "general-trias", "name": "General Trias" },
      { "id": "imus", "name": "Imus" },
      { "id": "indang", "name": "Indang" },
      { "id": "kawit", "name": "Kawit" },
      { "id": "magallanes", "name": "Magallanes" },
      { "id": "maragondon", "name": "Maragondon" },
      { "id": "mendez", "name": "Mendez" },
      { "id": "naic", "name": "Naic" },
      { "id": "noveleta", "name": "Noveleta" },
      { "id": "rosario", "name": "Rosario" },
      { "id": "silang", "name": "Silang" },
      { "id": "tagaytay", "name": "Tagaytay" },
      { "id": "tanza", "name": "Tanza" },
      { "id": "ternate", "name": "Ternate" },
      { "id": "trece-martires", "name": "Trece Martires" }
    ],
    "rizal": [
      { "id": "angono", "name": "Angono" },
      { "id": "antipolo", "name": "Antipolo" },
      { "id": "baras", "name": "Baras" },
      { "id": "binangonan", "name": "Binangonan" },
      { "id": "cainta", "name": "Cainta" },
      { "id": "cardona", "name": "Cardona" },
      { "id": "jalajala", "name": "Jalajala" },
      { "id": "morong", "name": "Morong" },
      { "id": "pililla", "name": "Pililla" },
      { "id": "rodriguez", "name": "Rodriguez" },
      { "id": "san-mateo", "name": "San Mateo" },
      { "id": "tanay", "name": "Tanay" },
      { "id": "taytay", "name": "Taytay" },
      { "id": "teresa", "name": "Teresa" }
    ],
    "bulacan": [
      { "id": "angat", "name": "Angat" },
      { "id": "balagtas", "name": "Balagtas" },
      { "id": "baliuag", "name": "Baliuag" },
      { "id": "bocaue", "name": "Bocaue" },
      { "id": "bulakan", "name": "Bulakan" },
      { "id": "bustos", "name": "Bustos" },
      { "id": "calumpit", "name": "Calumpit" },
      { "id": "doña-remedios-trinidad", "name": "Doña Remedios Trinidad" },
      { "id": "guiguinto", "name": "Guiguinto" },
      { "id": "hagonoy", "name": "Hagonoy" },
      { "id": "malolos", "name": "Malolos" },
      { "id": "marilao", "name": "Marilao" },
      { "id": "meycauayan", "name": "Meycauayan" },
      { "id": "norzagaray", "name": "Norzagaray" },
      { "id": "obando", "name": "Obando" },
      { "id": "pandi", "name": "Pandi" },
      { "id": "paombong", "name": "Paombong" },
      { "id": "plaridel", "name": "Plaridel" },
      { "id": "pulilan", "name": "Pulilan" },
      { "id": "san-ildefonso", "name": "San Ildefonso" },
      { "id": "san-jose-del-monte", "name": "San Jose del Monte" },
      { "id": "san-miguel", "name": "San Miguel" },
      { "id": "san-rafael", "name": "San Rafael" },
      { "id": "santa-maria", "name": "Santa Maria" }
    ],
    "pampanga": [
      { "id": "angeles", "name": "Angeles" },
      { "id": "apalit", "name": "Apalit" },
      { "id": "arayat", "name": "Arayat" },
      { "id": "bacolor", "name": "Bacolor" },
      { "id": "candaba", "name": "Candaba" },
      { "id": "floridablanca", "name": "Floridablanca" },
      { "id": "guagua", "name": "Guagua" },
      { "id": "lubao", "name": "Lubao" },
      { "id": "mabalacat", "name": "Mabalacat" },
      { "id": "macabebe", "name": "Macabebe" },
      { "id": "magalang", "name": "Magalang" },
      { "id": "masantol", "name": "Masantol" },
      { "id": "mexico", "name": "Mexico" },
      { "id": "minalin", "name": "Minalin" },
      { "id": "porac", "name": "Porac" },
      { "id": "san-fernando", "name": "San Fernando" },
      { "id": "san-luis", "name": "San Luis" },
      { "id": "san-simon", "name": "San Simon" },
      { "id": "santa-ana", "name": "Santa Ana" },
      { "id": "santa-rita", "name": "Santa Rita" },
      { "id": "santo-tomas", "name": "Santo Tomas" },
      { "id": "sasmuan", "name": "Sasmuan" }
    ],
    "bataan": [
      { "id": "abucay", "name": "Abucay" },
      { "id": "bagac", "name": "Bagac" },
      { "id": "balanga", "name": "Balanga" },
      { "id": "dinalupihan", "name": "Dinalupihan" },
      { "id": "hermosa", "name": "Hermosa" },
      { "id": "limay", "name": "Limay" },
      { "id": "mariveles", "name": "Mariveles" },
      { "id": "morong", "name": "Morong" },
      { "id": "orani", "name": "Orani" },
      { "id": "orion", "name": "Orion" },
      { "id": "pilar", "name": "Pilar" },
      { "id": "samal", "name": "Samal" }
    ],
    "nueva-ecija": [
      { "id": "aliaga", "name": "Aliaga" },
      { "id": "bongabon", "name": "Bongabon" },
      { "id": "cabanatuan", "name": "Cabanatuan" },
      { "id": "cabiao", "name": "Cabiao" },
      { "id": "carranglan", "name": "Carranglan" },
      { "id": "cuyapo", "name": "Cuyapo" },
      { "id": "gabaldon", "name": "Gabaldon" },
      { "id": "gapan", "name": "Gapan" },
      { "id": "general-mamerto-natividad", "name": "General Mamerto Natividad" },
      { "id": "general-tinio", "name": "General Tinio" },
      { "id": "guimba", "name": "Guimba" },
      { "id": "jaen", "name": "Jaen" },
      { "id": "laur", "name": "Laur" },
      { "id": "licab", "name": "Licab" },
      { "id": "llanera", "name": "Llanera" },
      { "id": "lupao", "name": "Lupao" },
      { "id": "muñoz", "name": "Muñoz" },
      { "id": "nampicuan", "name": "Nampicuan" },
      { "id": "palayan", "name": "Palayan" },
      { "id": "pantabangan", "name": "Pantabangan" },
      { "id": "peñaranda", "name": "Peñaranda" },
      { "id": "quezon", "name": "Quezon" },
      { "id": "rizal", "name": "Rizal" },
      { "id": "san-antonio", "name": "San Antonio" },
      { "id": "san-isidro", "name": "San Isidro" },
      { "id": "san-jose", "name": "San Jose" },
      { "id": "san-leonardo", "name": "San Leonardo" },
      { "id": "santa-rosa", "name": "Santa Rosa" },
      { "id": "santo-domingo", "name": "Santo Domingo" },
      { "id": "talavera", "name": "Talavera" },
      { "id": "talugtug", "name": "Talugtug" },
      { "id": "zaragoza", "name": "Zaragoza" }
    ],
    "tarlac": [
      { "id": "anao", "name": "Anao" },
      { "id": "bamban", "name": "Bamban" },
      { "id": "camiling", "name": "Camiling" },
      { "id": "capas", "name": "Capas" },
      { "id": "concepcion", "name": "Concepcion" },
      { "id": "gerona", "name": "Gerona" },
      { "id": "la-paz", "name": "La Paz" },
      { "id": "mayantoc", "name": "Mayantoc" },
      { "id": "moncada", "name": "Moncada" },
      { "id": "paniqui", "name": "Paniqui" },
      { "id": "pura", "name": "Pura" },
      { "id": "ramos", "name": "Ramos" },
      { "id": "san-clemente", "name": "San Clemente" },
      { "id": "san-manuel", "name": "San Manuel" },
      { "id": "santa-ignacia", "name": "Santa Ignacia" },
      { "id": "tarlac-city", "name": "Tarlac City" },
      { "id": "victoria", "name": "Victoria" }
    ],
    "zambales": [
      { "id": "botolan", "name": "Botolan" },
      { "id": "candelaria", "name": "Candelaria" },
      { "id": "castillejos", "name": "Castillejos" },
      { "id": "iba", "name": "Iba" },
      { "id": "masinloc", "name": "Masinloc" },
      { "id": "olongapo", "name": "Olongapo" },
      { "id": "palauig", "name": "Palauig" },
      { "id": "san-antonio", "name": "San Antonio" },
      { "id": "san-felipe", "name": "San Felipe" },
      { "id": "san-marceloino", "name": "San Marcelino" },
      { "id": "san-narciso", "name": "San Narciso" },
      { "id": "santa-cruz", "name": "Santa Cruz" },
      { "id": "subic", "name": "Subic" }
    ],
    "aurora": [
      { "id": "baler", "name": "Baler" },
      { "id": "casiguran", "name": "Casiguran" },
      { "id": "dilasag", "name": "Dilasag" },
      { "id": "dinalungan", "name": "Dinalungan" },
      { "id": "dingalan", "name": "Dingalan" },
      { "id": "dipaculao", "name": "Dipaculao" },
      { "id": "maria-aurora", "name": "Maria Aurora" },
      { "id": "san-luis", "name": "San Luis" }
    ],
    "batangas": [
      { "id": "agoncillo", "name": "Agoncillo" },
      { "id": "alitagtag", "name": "Alitagtag" },
      { "id": "balayan", "name": "Balayan" },
      { "id": "balete", "name": "Balete" },
      { "id": "bauan", "name": "Bauan" },
      { "id": "calaca", "name": "Calaca" },
      { "id": "calatagan", "name": "Calatagan" },
      { "id": "cuenca", "name": "Cuenca" },
      { "id": "ibaan", "name": "Ibaan" },
      { "id": "laurel", "name": "Laurel" },
      { "id": "lemery", "name": "Lemery" },
      { "id": "lian", "name": "Lian" },
      { "id": "lipa", "name": "Lipa" },
      { "id": "lobo", "name": "Lobo" },
      { "id": "mabini", "name": "Mabini" },
      { "id": "malvar", "name": "Malvar" },
      { "id": "mataasnakahoy", "name": "Mataasnakahoy" },
      { "id": "nasugbu", "name": "Nasugbu" },
      { "id": "padre-garcia", "name": "Padre Garcia" },
      { "id": "rosario", "name": "Rosario" },
      { "id": "san-jose", "name": "San Jose" },
      { "id": "san-juan", "name": "San Juan" },
      { "id": "san-luis", "name": "San Luis" },
      { "id": "san-nicolas", "name": "San Nicolas" },
      { "id": "san-pascual", "name": "San Pascual" },
      { "id": "santa-teresita", "name": "Santa Teresita" },
      { "id": "santo-tomas", "name": "Santo Tomas" },
      { "id": "taal", "name": "Taal" },
      { "id": "talisay", "name": "Talisay" },
      { "id": "tanauan", "name": "Tanauan" },
      { "id": "taysan", "name": "Taysan" },
      { "id": "tingloy", "name": "Tingloy" },
      { "id": "tuy", "name": "Tuy" }
    ],
    "quezon": [
      { "id": "agdangan", "name": "Agdangan" },
      { "id": "alabat", "name": "Alabat" },
      { "id": "atimonan", "name": "Atimonan" },
      { "id": "buenavista", "name": "Buenavista" },
      { "id": "burdeos", "name": "Burdeos" },
      { "id": "calauag", "name": "Calauag" },
      { "id": "candelaria", "name": "Candelaria" },
      { "id": "catanauan", "name": "Catanauan" },
      { "id": "dolores", "name": "Dolores" },
      { "id": "general-luna", "name": "General Luna" },
      { "id": "general-nakar", "name": "General Nakar" },
      { "id": "guinayangan", "name": "Guinayangan" },
      { "id": "gumaca", "name": "Gumaca" },
      { "id": "infanta", "name": "Infanta" },
      { "id": "jomalig", "name": "Jomalig" },
      { "id": "lopez", "name": "Lopez" },
      { "id": "lucban", "name": "Lucban" },
      { "id": "lucena", "name": "Lucena" },
      { "id": "macalelon", "name": "Macalelon" },
      { "id": "mauban", "name": "Mauban" },
      { "id": "mulanay", "name": "Mulanay" },
      { "id": "padre-burgos", "name": "Padre Burgos" },
      { "id": "pagbilao", "name": "Pagbilao" },
      { "id": "panukulan", "name": "Panukulan" },
      { "id": "patnanungan", "name": "Patnanungan" },
      { "id": "perez", "name": "Perez" },
      { "id": "pitogo", "name": "Pitogo" },
      { "id": "plaridel", "name": "Plaridel" },
      { "id": "polillo", "name": "Polillo" },
      { "id": "quezon", "name": "Quezon" },
      { "id": "real", "name": "Real" },
      { "id": "sampaloc", "name": "Sampaloc" },
      { "id": "san-andres", "name": "San Andres" },
      { "id": "san-antonio", "name": "San Antonio" },
      { "id": "san-francisco", "name": "San Francisco" },
      { "id": "san-narciso", "name": "San Narciso" },
      { "id": "sariaya", "name": "Sariaya" },
      { "id": "tagkawayan", "name": "Tagkawayan" },
      { "id": "tayabas", "name": "Tayabas" },
      { "id": "tiaong", "name": "Tiaong" },
      { "id": "unisan", "name": "Unisan" }
    ]
  },
  "barangays": {
    "manila": [
      { "id": "binondo", "name": "Binondo" },
      { "id": "ermita", "name": "Ermita" },
      { "id": "intramuros", "name": "Intramuros" },
      { "id": "malate", "name": "Malate" },
      { "id": "paco", "name": "Paco" },
      { "id": "pandacan", "name": "Pandacan" },
      { "id": "port-area", "name": "Port Area" },
      { "id": "quiapo", "name": "Quiapo" },
      { "id": "sampaloc", "name": "Sampaloc" },
      { "id": "san-andres", "name": "San Andres" },
      { "id": "san-miguel", "name": "San Miguel" },
      { "id": "san-nicolas", "name": "San Nicolas" },
      { "id": "santa-ana", "name": "Santa Ana" },
      { "id": "santa-cruz", "name": "Santa Cruz" },
      { "id": "santa-mesa", "name": "Santa Mesa" },
      { "id": "tondo", "name": "Tondo" }
    ],
    "quezon-city": [
      { "id": "bagong-silangan", "name": "Bagong Silangan" },
      { "id": "batasan-hills", "name": "Batasan Hills" },
      { "id": "commonwealth", "name": "Commonwealth" },
      { "id": "diliman", "name": "Diliman" },
      { "id": "east-kamias", "name": "East Kamias" },
      { "id": "holy-spirit", "name": "Holy Spirit" },
      { "id": "katipunan", "name": "Katipunan" },
      { "id": "loyola-heights", "name": "Loyola Heights" },
      { "id": "matandang-balara", "name": "Matandang Balara" },
      { "id": "novaliches-proper", "name": "Novaliches Proper" },
      { "id": "pansol", "name": "Pansol" },
      { "id": "payatas", "name": "Payatas" },
      { "id": "pinyahan", "name": "Pinyahan" },
      { "id": "project-4", "name": "Project 4" },
      { "id": "project-6", "name": "Project 6" },
      { "id": "project-7", "name": "Project 7" },
      { "id": "project-8", "name": "Project 8" },
      { "id": "sangandaan", "name": "Sangandaan" },
      { "id": "santa-cruz", "name": "Santa Cruz" },
      { "id": "santo-cristo", "name": "Santo Cristo" },
      { "id": "santo-domingo", "name": "Santo Domingo" },
      { "id": "socorro", "name": "Socorro" },
      { "id": "tatalon", "name": "Tatalon" },
      { "id": "up-campus", "name": "UP Campus" },
      { "id": "veterans-village", "name": "Veterans Village" },
      { "id": "west-kamias", "name": "West Kamias" }
    ],
    "calamba": [
      { "id": "bagong-kalsada", "name": "Bagong Kalsada" },
      { "id": "banco", "name": "Banco" },
      { "id": "banlic", "name": "Banlic" },
      { "id": "bubukal", "name": "Bubukal" },
      { "id": "burol", "name": "Burol" },
      { "id": "camaligan", "name": "Camaligan" },
      { "id": "canlubang", "name": "Canlubang" },
      { "id": "halang", "name": "Halang" },
      { "id": "hornalan", "name": "Hornalan" },
      { "id": "kay-anlog", "name": "Kay-anlog" },
      { "id": "la-mesa", "name": "La Mesa" },
      { "id": "lawa", "name": "Lawa" },
      { "id": "lecaros", "name": "Lecaros" },
      { "id": "lingga", "name": "Lingga" },
      { "id": "looc", "name": "Looc" },
      { "id": "mabato", "name": "Mabato" },
      { "id": "majada-labas", "name": "Majada Labas" },
      { "id": "makiling", "name": "Makiling" },
      { "id": "mapagong", "name": "Mapagong" },
      { "id": "masili", "name": "Masili" },
      { "id": "maunong", "name": "Maunong" },
      { "id": "mayapa", "name": "Mayapa" },
      { "id": "paciano-rizal", "name": "Paciano Rizal" },
      { "id": "palingon", "name": "Palingon" },
      { "id": "palo-alto", "name": "Palo Alto" },
      { "id": "pansol", "name": "Pansol" },
      { "id": "parian", "name": "Parian" },
      { "id": "prinza", "name": "Prinza" },
      { "id": "punta", "name": "Punta" },
      { "id": "puting-lupa", "name": "Puting Lupa" },
      { "id": "real", "name": "Real" },
      { "id": "saimsim", "name": "Saimsim" },
      { "id": "sucol", "name": "Sucol" },
      { "id": "turbina", "name": "Turbina" },
      { "id": "ulango", "name": "Ulango" },
      { "id": "uzon", "name": "Uzon" }
    ],
    "santa-rosa": [
      { "id": "aplaya", "name": "Aplaya" },
      { "id": "balibago", "name": "Balibago" },
      { "id": "caingin", "name": "Caingin" },
      { "id": "dila", "name": "Dila" },
      { "id": "dita", "name": "Dita" },
      { "id": "don-jose", "name": "Don Jose" },
      { "id": "ibabang-ayo", "name": "Ibabang Ayo" },
      { "id": "ilaya", "name": "Ilaya" },
      { "id": "labas", "name": "Labas" },
      { "id": "macabling", "name": "Macabling" },
      { "id": "malitlit", "name": "Malitlit" },
      { "id": "malusak", "name": "Malusak" },
      { "id": "pooc", "name": "Pooc" },
      { "id": "pulong-santa-cruz", "name": "Pulong Santa Cruz" },
      { "id": "santo-domingo", "name": "Santo Domingo" },
      { "id": "sinalhan", "name": "Sinalhan" },
      { "id": "tagapo", "name": "Tagapo" }
    ],
    "cabuyao": [
      { "id": "banaybanay", "name": "Banaybanay" },
      { "id": "banlic", "name": "Banlic" },
      { "id": "bigaa", "name": "Bigaa" },
      { "id": "butong", "name": "Butong" },
      { "id": "casile", "name": "Casile" },
      { "id": "diezmo", "name": "Diezmo" },
      { "id": "gulod", "name": "Gulod" },
      { "id": "mamatid", "name": "Mamatid" },
      { "id": "marinig", "name": "Marinig" },
      { "id": "niugan", "name": "Niugan" },
      { "id": "pittland", "name": "Pittland" },
      { "id": "pulo", "name": "Pulo" },
      { "id": "sala", "name": "Sala" },
      { "id": "salinas", "name": "Salinas" },
      { "id": "santo-tomas", "name": "Santo Tomas" },
      { "id": "villa-nueva", "name": "Villa Nueva" }
    ],
    "san-pedro": [
      { "id": "bagong-silang", "name": "Bagong Silang" },
      { "id": "calendola", "name": "Calendola" },
      { "id": "chrysanthemum", "name": "Chrysanthemum" },
      { "id": "cuyab", "name": "Cuyab" },
      { "id": "estrellita", "name": "Estrellita" },
      { "id": "fatima", "name": "Fatima" },
      { "id": "g.s.i.s", "name": "G.S.I.S" },
      { "id": "landayan", "name": "Landayan" },
      { "id": "langgam", "name": "Langgam" },
      { "id": "laran", "name": "Laran" },
      { "id": "magdalena", "name": "Magdalena" },
      { "id": "maharlika", "name": "Maharlika" },
      { "id": "narag", "name": "Narag" },
      { "id": "nueva", "name": "Nueva" },
      { "id": "pacita", "name": "Pacita" },
      { "id": "poblacion", "name": "Poblacion" },
      { "id": "rivera", "name": "Rivera" },
      { "id": "rosario", "name": "Rosario" },
      { "id": "sampaguita", "name": "Sampaguita" },
      { "id": "san-antonio", "name": "San Antonio" },
      { "id": "san-roque", "name": "San Roque" },
      { "id": "santo-nino", "name": "Santo Niño" },
      { "id": "sunnyville", "name": "Sunnyville" },
      { "id": "united-bayanihan", "name": "United Bayanihan" },
      { "id": "veterans", "name": "Veterans" }
    ],
    "biñan": [
      { "id": "bagong-silang", "name": "Bagong Silang" },
      { "id": "bambang", "name": "Bambang" },
      { "id": "buli", "name": "Buli" },
      { "id": "bungahan", "name": "Bungahan" },
      { "id": "canlalay", "name": "Canlalay" },
      { "id": "casile", "name": "Casile" },
      { "id": "de-la-paz", "name": "De La Paz" },
      { "id": "ganado", "name": "Ganado" },
      { "id": "langkiwa", "name": "Langkiwa" },
      { "id": "loma", "name": "Loma" },
      { "id": "malaban", "name": "Malaban" },
      { "id": "malamig", "name": "Malamig" },
      { "id": "mampalasan", "name": "Mampalasan" },
      { "id": "platero", "name": "Platero" },
      { "id": "poblacion", "name": "Poblacion" },
      { "id": "santo-tomas", "name": "Santo Tomas" },
      { "id": "soro-soro", "name": "Soro-soro" },
      { "id": "south-silangan", "name": "South Silangan" },
      { "id": "timpas", "name": "Timpas" },
      { "id": "tubigan", "name": "Tubigan" },
      { "id": "zapote", "name": "Zapote" }
    ],
    "dasmarinas": [
      { "id": "burol", "name": "Burol" },
      { "id": "dasmariñas-bagong-bayan", "name": "Dasmariñas Bagong Bayan" },
      { "id": "emmanuel-bergado", "name": "Emmanuel Bergado" },
      { "id": "fatima", "name": "Fatima" },
      { "id": "francisco-paule", "name": "Francisco Paule" },
      { "id": "langkaan", "name": "Langkaan" },
      { "id": "luciano", "name": "Luciano" },
      { "id": "luzviminda", "name": "Luzviminda" },
      { "id": "paliparan", "name": "Paliparan" },
      { "id": "poblacion", "name": "Poblacion" },
      { "id": "sampaguita", "name": "Sampaguita" },
      { "id": "san-agustin", "name": "San Agustin" },
      { "id": "san-antonio", "name": "San Antonio" },
      { "id": "san-dionisio", "name": "San Dionisio" },
      { "id": "san-esteban", "name": "San Esteban" },
      { "id": "san-francisco", "name": "San Francisco" },
      { "id": "san-isidro", "name": "San Isidro" },
      { "id": "san-jose", "name": "San Jose" },
      { "id": "san-juan", "name": "San Juan" },
      { "id": "san-lorenzo", "name": "San Lorenzo" },
      { "id": "san-manuel", "name": "San Manuel" },
      { "id": "san-miguel", "name": "San Miguel" },
      { "id": "san-nicolas", "name": "San Nicolas" },
      { "id": "san-pedro", "name": "San Pedro" },
      { "id": "santa-cristina", "name": "Santa Cristina" },
      { "id": "santa-cruz", "name": "Santa Cruz" },
      { "id": "santa-fe", "name": "Santa Fe" },
      { "id": "santa-lucia", "name": "Santa Lucia" },
      { "id": "santa-maria", "name": "Santa Maria" },
      { "id": "santo-cristo", "name": "Santo Cristo" },
      { "id": "santo-domingo", "name": "Santo Domingo" },
      { "id": "victoria", "name": "Victoria" }
    ],
    "imus": [
      { "id": "alapan", "name": "Alapan" },
      { "id": "anabu-i", "name": "Anabu I" },
      { "id": "anabu-ii", "name": "Anabu II" },
      { "id": "bagong-silang", "name": "Bagong Silang" },
      { "id": "bayan-luma", "name": "Bayan Luma" },
      { "id": "bucandala", "name": "Bucandala" },
      { "id": "buho", "name": "Buho" },
      { "id": "carsadang-bago", "name": "Carsadang Bago" },
      { "id": "florentino-duenas", "name": "Florentino Dueñas" },
      { "id": "gen-ricarte", "name": "Gen. Ricarte" },
      { "id": "gov-d-m-camerino", "name": "Gov. D.M. Camerino" },
      { "id": "habay", "name": "Habay" },
      { "id": "hugo-perez", "name": "Hugo Perez" },
      { "id": "imus", "name": "Imus" },
      { "id": "kapitan-pepe", "name": "Kapitan Pepe" },
      { "id": "luklukan", "name": "Luklukan" },
      { "id": "malagasang-i", "name": "Malagasang I" },
      { "id": "malagasang-ii", "name": "Malagasang II" },
      { "id": "mariano-espeleta", "name": "Mariano Espeleta" },
      { "id": "medicion-i", "name": "Medicion I" },
      { "id": "medicion-ii", "name": "Medicion II" },
      { "id": "medicion-iii", "name": "Medicion III" },
      { "id": "medicion-iv", "name": "Medicion IV" },
      { "id": "paco", "name": "Paco" },
      { "id": "palico", "name": "Palico" },
      { "id": "pasong-buaya", "name": "Pasong Buaya" },
      { "id": "poblacion-i", "name": "Poblacion I" },
      { "id": "poblacion-ii", "name": "Poblacion II" },
      { "id": "poblacion-iii", "name": "Poblacion III" },
      { "id": "poblacion-iv", "name": "Poblacion IV" },
      { "id": "sampaguita", "name": "Sampaguita" },
      { "id": "santo-nino", "name": "Santo Niño" },
      { "id": "tanzang-luma", "name": "Tanzang Luma" },
      { "id": "toclong", "name": "Toclong" },
      { "id": "wakas", "name": "Wakas" }
    ],
    "general-trias": [
      { "id": "alangilan", "name": "Alangilan" },
      { "id": "arandia", "name": "Arandia" },
      { "id": "bagong-silang", "name": "Bagong Silang" },
      { "id": "balsahan", "name": "Balsahan" },
      { "id": "biclatan", "name": "Biclatan" },
      { "id": "bucal", "name": "Bucal" },
      { "id": "burol", "name": "Burol" },
      { "id": "cavite", "name": "Cavite" },
      { "id": "concepcion", "name": "Concepcion" },
      { "id": "dulong-bayan", "name": "Dulong Bayan" },
      { "id": "francisco", "name": "Francisco" },
      { "id": "gentri", "name": "Gentri" },
      { "id": "herrera", "name": "Herrera" },
      { "id": "hugo-perez", "name": "Hugo Perez" },
      { "id": "javalera", "name": "Javalera" },
      { "id": "manggahan", "name": "Manggahan" },
      { "id": "manuel-t-roxas", "name": "Manuel T. Roxas" },
      { "id": "marcos-alvarez", "name": "Marcos Alvarez" },
      { "id": "palangue", "name": "Palangue" },
      { "id": "panamitan", "name": "Panamitan" },
      { "id": "pasong-camachile", "name": "Pasong Camachile" },
      { "id": "pasong-kawayan", "name": "Pasong Kawayan" },
      { "id": "pinagtipunan", "name": "Pinagtipunan" },
      { "id": "sabang", "name": "Sabang" },
      { "id": "salitran", "name": "Salitran" },
      { "id": "santiago", "name": "Santiago" },
      { "id": "santol", "name": "Santol" },
      { "id": "tartaria", "name": "Tartaria" },
      { "id": "tejero", "name": "Tejero" },
      { "id": "tugbok", "name": "Tugbok" },
      { "id": "vibora", "name": "Vibora" }
    ]
  }
}


